setup.py
sqlrest/__init__.py
sqlrest/caching.py
sqlrest/config.spec.py
sqlrest/database.py
sqlrest/log.py
sqlrest/server.py
sqlrest.egg-info/PKG-INFO
sqlrest.egg-info/SOURCES.txt
sqlrest.egg-info/dependency_links.txt
sqlrest.egg-info/requires.txt
sqlrest.egg-info/top_level.txt