Metadata-Version: 1.1
Name: sqlrest
Version: 0.3.0
Summary: Instant REST APIs for SQL tables
Home-page: http://github.com/duckworthd/sqlrest
Author: Daniel Duckworth
Author-email: duckworthd@gmail.com
License: BSD
Keywords: database sql rest api
Platform: UNKNOWN
Classifier: Development Status :: 4 - Beta
Classifier: License :: OSI Approved :: BSD License
Classifier: Operating System :: OS Independent
Classifier: Programming Language :: Python
